polars_holidays-0.1.1.dist-info/METADATA
polars_holidays-0.1.1.dist-info/WHEEL
polars_holidays-0.1.1.dist-info/licenses/LICENSE
polars_holidays/__init__.py
polars_holidays/_internal.abi3.so
polars_holidays/_internal.pyi
polars_holidays/typing.py
polars_holidays-0.1.1.dist-info/RECORD
